ebooklet/__init__.py
ebooklet/main.py
ebooklet/remote.py
ebooklet/utils.py
ebooklet-0.5.10.dist-info/METADATA
ebooklet-0.5.10.dist-info/WHEEL
ebooklet-0.5.10.dist-info/licenses/LICENSE
ebooklet-0.5.10.dist-info/RECORD
