Metadata-Version: 2.4
Name: ebooklet
Version: 0.5.10
Summary: Organise all your data in key/value booklets and sync them with S3
Project-URL: Documentation, https://mullenkamp.github.io/ebooklet/
Project-URL: Source, https://github.com/mullenkamp/ebooklet
Author-email: Mike <mullenkamp1@gmail.com>
License-File: LICENSE
Keywords: booklet,dbm,s3,shelve
Classifier: Programming Language :: Python :: 3 :: Only
Requires-Python: >=3.10
Requires-Dist: booklet>=0.9.2
Requires-Dist: s3func>=0.7.2
Requires-Dist: urllib3>=2
